[
    {
        "caption":"Lyon accueille la finale mondiale des Worldskills 2024",
        "src": "worldskills-2024-p.jpg",
        "alt": "worldskills 2024 picture"
    },
    {
        "caption":"Forum des associations 2024",
        "src":"fda-p.jpg",
        "alt":"fda picture"

    },
    {
        "caption":"Lyon Kayak",
        "src":"lyon-kayak-p-0.jpg",
        "alt":"lyon kayak picture"

    },
    {
        "caption":"La semaine bleue 2024",
        "src":"semaine-bleue-2024-p.jpg",
        "alt":"semaine bleue 2024 picture"
    },
    {
        "caption":"Le Village des Métiers",
        "src":"village-des-metiers-p.jpg",
        "alt":"village des metiers picture"

    },
    {
        "caption":"Les Journées Portes Ouvertes des Entreprises",
        "src":"journees_portes_ouvertes_entreprises_2023_p.jpg",
        "alt":"journees portes ouvertes entreprises 2023 picture"
    }

]